abstract class Class_ck {
   static int a = -1;
   static int b = 0;
   static int c = 0;
   static Class_aa[][][] d;
   static int e = 0;
   static int f;
   static int g;
   static Class_r h = Class_tc.a(43, "compass");

   static final void a(byte param0) {
      // $VF: Couldn't be decompiled
      // Please report this to the Vineflower issue tracker, at https://github.com/Vineflower/vineflower/issues with a copy of the class file (if you have the rights to distribute it!)
      // java.lang.RuntimeException: parsing failure!
      //   at org.jetbrains.java.decompiler.modules.decompiler.decompose.DomHelper.parseGraph(DomHelper.java:211)
      //   at org.jetbrains.java.decompiler.main.rels.MethodProcessor.codeToJava(MethodProcessor.java:166)
      //
      // Bytecode:
      // 000: getstatic client.lb I
      // 003: istore 11
      // 005: getstatic Class_f.T LClass_cc;
      // 008: bipush 122
      // 00a: invokevirtual Class_cc.s (I)V
      // 00d: getstatic Class_ck.g I
      // 010: bipush 1
      // 011: iadd
      // 012: putstatic Class_ck.g I
      // 015: getstatic Class_f.T LClass_cc;
      // 018: bipush 0
      // 019: bipush 8
      // 01b: invokevirtual Class_cc.e (BI)I
      // 01e: istore 1
      // 01f: iload 1
      // 020: bipush -1
      // 021: ixor
      // 022: getstatic Class_ke.p I
      // 025: bipush -1
      // 026: ixor
      // 027: if_icmple 051
      // 02a: iload 1
      // 02b: istore 2
      // 02c: iload 11
      // 02e: ifeq 046
      // 031: getstatic Class_ih.R [I
      // 034: getstatic Class_ja.w I
      // 037: dup
      // 038: bipush 1
      // 039: iadd
      // 03a: putstatic Class_ja.w I
      // 03d: getstatic Class_kg.v [I
      // 040: iload 2
      // 041: iaload
      // 042: iastore
      // 043: iinc 2 1
      // 046: getstatic Class_ke.p I
      // 049: bipush -1
      // 04a: ixor
      // 04b: iload 2
      // 04c: bipush -1
      // 04d: ixor
      // 04e: if_icmplt 031
      // 051: iload 1
      // 052: bipush -1
      // 053: ixor
      // 054: getstatic Class_ke.p I
      // 057: bipush -1
      // 058: ixor
      // 059: if_icmpge 066
      // 05c: new java/lang/RuntimeException
      // 05f: dup
      // 060: ldc "gnpov1"
      // 062: invokespecial java/lang/RuntimeException.<init> (Ljava/lang/String;)V
      // 065: athrow
      // 066: bipush 0
      // 067: putstatic Class_ke.p I
      // 06a: bipush 0
      // 06b: istore 2
      // 06c: bipush 112
      // 06e: bipush 46
      // 070: iload 0
      // 071: isub
      // 072: bipush 63
      // 074: idiv
      // 075: idiv
      // 076: istore 3
      // 077: iload 11
      // 079: ifeq 1d2
      // 07c: getstatic Class_kg.v [I
      // 07f: iload 2
      // 080: iaload
      // 081: istore 4
      // 083: getstatic Class_rf.a [LClass_eh;
      // 086: iload 4
      // 088: aaload
      // 089: astore 5
      // 08b: getstatic Class_f.T LClass_cc;
      // 08e: bipush 0
      // 08f: bipush 1
      // 090: invokevirtual Class_cc.e (BI)I
      // 093: istore 6
      // 095: iload 6
      // 097: bipush -1
      // 098: ixor
      // 099: bipush -1
      // 09a: if_icmpne 0b9
      // 09d: getstatic Class_kg.v [I
      // 0a0: getstatic Class_ke.p I
      // 0a3: dup
      // 0a4: bipush 1
      // 0a5: iadd
      // 0a6: putstatic Class_ke.p I
      // 0a9: iload 4
      // 0ab: iastore
      // 0ac: aload 5
      // 0ae: getstatic Class_be.C I
      // 0b1: putfield Class_ta.vb I
      // 0b4: iload 11
      // 0b6: ifeq 1cf
      // 0b9: getstatic Class_f.T LClass_cc;
      // 0bc: bipush 0
      // 0bd: bipush 2
      // 0be: invokevirtual Class_cc.e (BI)I
      // 0c1: istore 7
      // 0c3: iload 7
      // 0c5: ifne 0f3
      // 0c8: getstatic Class_kg.v [I
      // 0cb: getstatic Class_ke.p I
      // 0ce: dup
      // 0cf: bipush 1
      // 0d0: iadd
      // 0d1: putstatic Class_ke.p I
      // 0d4: iload 4
      // 0d6: iastore
      // 0d7: aload 5
      // 0d9: getstatic Class_be.C I
      // 0dc: putfield Class_ta.vb I
      // 0df: getstatic Class_cc.Db [I
      // 0e2: getstatic Class_uf.U I
      // 0e5: dup
      // 0e6: bipush 1
      // 0e7: iadd
      // 0e8: putstatic Class_uf.U I
      // 0eb: iload 4
      // 0ed: iastore
      // 0ee: iload 11
      // 0f0: ifeq 1cf
      // 0f3: iload 7
      // 0f5: bipush -1
      // 0f6: ixor
      // 0f7: bipush -2
      // 0f9: if_icmpne 14e
      // 0fc: getstatic Class_kg.v [I
      // 0ff: getstatic Class_ke.p I
      // 102: dup
      // 103: bipush 1
      // 104: iadd
      // 105: putstatic Class_ke.p I
      // 108: iload 4
      // 10a: iastore
      // 10b: aload 5
      // 10d: getstatic Class_be.C I
      // 110: putfield Class_ta.vb I
      // 113: getstatic Class_f.T LClass_cc;
      // 116: bipush 0
      // 117: bipush 3
      // 118: invokevirtual Class_cc.e (BI)I
      // 11b: istore 8
      // 11d: aload 5
      // 11f: bipush 0
      // 120: iload 8
      // 122: bipush 21
      // 124: invokevirtual Class_ta.a (ZIB)V
      // 127: getstatic Class_f.T LClass_cc;
      // 12a: bipush 0
      // 12b: bipush 1
      // 12c: invokevirtual Class_cc.e (BI)I
      // 12f: istore 9
      // 131: iload 9
      // 133: bipush -1
      // 134: ixor
      // 135: bipush -2
      // 137: if_icmpne 1cf
      // 13a: getstatic Class_cc.Db [I
      // 13d: getstatic Class_uf.U I
      // 140: dup
      // 141: bipush 1
      // 142: iadd
      // 143: putstatic Class_uf.U I
      // 146: iload 4
      // 148: iastore
      // 149: iload 11
      // 14b: ifeq 1cf
      // 14e: iload 7
      // 150: bipush 2
      // 151: if_icmpne 1b7
      // 154: getstatic Class_kg.v [I
      // 157: getstatic Class_ke.p I
      // 15a: dup
      // 15b: bipush 1
      // 15c: iadd
      // 15d: putstatic Class_ke.p I
      // 160: iload 4
      // 162: iastore
      // 163: aload 5
      // 165: getstatic Class_be.C I
      // 168: putfield Class_ta.vb I
      // 16b: getstatic Class_f.T LClass_cc;
      // 16e: bipush 0
      // 16f: bipush 3
      // 170: invokevirtual Class_cc.e (BI)I
      // 173: istore 8
      // 175: aload 5
      // 177: bipush 1
      // 178: iload 8
      // 17a: bipush 21
      // 17c: invokevirtual Class_ta.a (ZIB)V
      // 17f: getstatic Class_f.T LClass_cc;
      // 182: bipush 0
      // 183: bipush 3
      // 184: invokevirtual Class_cc.e (BI)I
      // 187: istore 9
      // 189: aload 5
      // 18b: bipush 1
      // 18c: iload 9
      // 18e: bipush 21
      // 190: invokevirtual Class_ta.a (ZIB)V
      // 193: getstatic Class_f.T LClass_cc;
      // 196: bipush 0
      // 197: bipush 1
      // 198: invokevirtual Class_cc.e (BI)I
      // 19b: istore 10
      // 19d: iload 10
      // 19f: bipush 1
      // 1a0: if_icmpne 1cf
      // 1a3: getstatic Class_cc.Db [I
      // 1a6: getstatic Class_uf.U I
      // 1a9: dup
      // 1aa: bipush 1
      // 1ab: iadd
      // 1ac: putstatic Class_uf.U I
      // 1af: iload 4
      // 1b1: iastore
      // 1b2: iload 11
      // 1b4: ifeq 1cf
      // 1b7: iload 7
      // 1b9: bipush 3
      // 1ba: if_icmpne 1cf
      // 1bd: getstatic Class_ih.R [I
      // 1c0: getstatic Class_ja.w I
      // 1c3: dup
      // 1c4: bipush 1
      // 1c5: iadd
      // 1c6: putstatic Class_ja.w I
      // 1c9: iload 4
      // 1cb: iastore
      // 1cc: goto 1cf
      // 1cf: iinc 2 1
      // 1d2: iload 2
      // 1d3: bipush -1
      // 1d4: ixor
      // 1d5: iload 1
      // 1d6: bipush -1
      // 1d7: ixor
      // 1d8: if_icmpgt 07c
      // 1db: return
      // 1dc: astore 1
      // 1dd: aload 1
      // 1de: new java/lang/StringBuffer
      // 1e1: dup
      // 1e2: ldc "ck.A("
      // 1e4: invokespecial java/lang/StringBuffer.<init> (Ljava/lang/String;)V
      // 1e7: iload 0
      // 1e8: invokevirtual java/lang/StringBuffer.append (I)Ljava/lang/StringBuffer;
      // 1eb: bipush 41
      // 1ed: invokevirtual java/lang/StringBuffer.append (C)Ljava/lang/StringBuffer;
      // 1f0: invokevirtual java/lang/StringBuffer.toString ()Ljava/lang/String;
      // 1f3: invokestatic Class_sh.a (Ljava/lang/Throwable;Ljava/lang/String;)LClass_ua;
      // 1f6: athrow
   }

   static final void a(byte var0, Class_cj var1) {
      try {
         if (var0 != 58) {
            a((byte)95, null);
         }

         f++;
         Class_lc.d = var1;
      } catch (RuntimeException var3) {
         throw Class_sh.a(var3, "ck.C(" + var0 + ',' + (var1 != null ? "{...}" : "null") + ')');
      }
   }

   public static void a(int var0) {
      try {
         d = null;
         h = null;
         if (var0 < 30) {
            d = null;
         }
      } catch (RuntimeException var2) {
         throw Class_sh.a(var2, "ck.B(" + var0 + ')');
      }
   }
}
